{"SourceCode": "{{\r\n  \"language\": \"Solidity\",\r\n  \"sources\": {\r\n    \"meme_dev/z23_09_03/PNDC.sol\": {\r\n      \"content\": \"// SPDX-License-Identifier: MIT\\npragma solidity ^0.8.0;\\n\\ninterface IERC20 {\\n    event Transfer(address indexed from, address indexed to, uint256 value);\\n\\n    event Approval(\\n        address indexed owner,\\n        address indexed spender,\\n        uint256 value\\n    );\\n\\n    function name() external view returns (string memory);\\n\\n    function symbol() external view returns (string memory);\\n\\n    function decimals() external view returns (uint8);\\n\\n    function totalSupply() external view returns (uint256);\\n\\n    function balanceOf(address account) external view returns (uint256);\\n\\n    function transfer(address to, uint256 amount) external returns (bool);\\n\\n    function allowance(address owner, address spender)\\n        external\\n        view\\n        returns (uint256);\\n\\n    function approve(address spender, uint256 amount) external returns (bool);\\n\\n    function transferFrom(\\n        address from,\\n        address to,\\n        uint256 amount\\n    ) external returns (bool);\\n}\\n\\ncontract ERC20 is IERC20 {\\n    mapping(address => uint256) private _balances;\\n\\n    mapping(address => mapping(address => uint256)) private _allowances;\\n\\n    uint256 private _totalSupply;\\n\\n    string private _name;\\n    string private _symbol;\\n    uint8 private _decimals;\\n\\n    constructor() {\\n        _symbol = \\\"PNDC\\\";\\n        _name = \\\"Pond Coin\\\";\\n        \\n        _decimals = 18;\\n        _totalSupply = 1000000000 * (10**_decimals);\\n\\n        _balances[msg.sender] = _totalSupply;\\n        emit Transfer(address(0), msg.sender, _totalSupply);\\n    }\\n\\n    function name() public view virtual override returns (string memory) {\\n        return _name;\\n    }\\n\\n    function symbol() public view virtual override returns (string memory) {\\n        return _symbol;\\n    }\\n\\n    function decimals() public view virtual override returns (uint8) {\\n        return _decimals;\\n    }\\n\\n    function totalSupply() public view virtual override returns (uint256) {\\n        return _totalSupply;\\n    }\\n\\n    function balanceOf(address account)\\n        public\\n        view\\n        virtual\\n        override\\n        returns (uint256)\\n    {\\n        return _balances[account];\\n    }\\n\\n    function transfer(address to, uint256 amount)\\n        public\\n        virtual\\n        override\\n        returns (bool)\\n    {\\n        address owner = msg.sender;\\n        _transfer(owner, to, amount);\\n        return true;\\n    }\\n\\n    function allowance(address owner, address spender)\\n        public\\n        view\\n        virtual\\n        override\\n        returns (uint256)\\n    {\\n        return _allowances[owner][spender];\\n    }\\n\\n    function approve(address spender, uint256 amount)\\n        public\\n        virtual\\n        override\\n        returns (bool)\\n    {\\n        address owner = msg.sender;\\n        _approve(owner, spender, amount);\\n        return true;\\n    }\\n\\n    function transferFrom(\\n        address from,\\n        address to,\\n        uint256 amount\\n    ) public virtual override returns (bool) {\\n        address spender = msg.sender;\\n        _spendAllowance(from, spender, amount);\\n        _transfer(from, to, amount);\\n        return true;\\n    }\\n\\n    function _transfer(\\n        address from,\\n        address to,\\n        uint256 amount\\n    ) internal virtual {\\n        require(from != address(0), \\\"ERC20: transfer from the zero address\\\");\\n        require(to != address(0), \\\"ERC20: transfer to the zero address\\\");\\n\\n        uint256 fromBalance = _balances[from];\\n        require(\\n            fromBalance >= amount,\\n            \\\"ERC20: transfer amount exceeds balance\\\"\\n        );\\n        unchecked {\\n            _balances[from] = fromBalance - amount;\\n        }\\n        _balances[to] += amount;\\n\\n        emit Transfer(from, to, amount);\\n    }\\n\\n    function _approve(\\n        address owner,\\n        address spender,\\n        uint256 amount\\n    ) internal virtual {\\n        require(owner != address(0), \\\"ERC20: approve from the zero address\\\");\\n        require(spender != address(0), \\\"ERC20: approve to the zero address\\\");\\n\\n        _allowances[owner][spender] = amount;\\n        emit Approval(owner, spender, amount);\\n    }\\n\\n    function _spendAllowance(\\n        address owner,\\n        address spender,\\n        uint256 amount\\n    ) internal virtual {\\n        uint256 currentAllowance = allowance(owner, spender);\\n        if (currentAllowance != type(uint256).max) {\\n            require(\\n                currentAllowance >= amount,\\n                \\\"ERC20: insufficient allowance\\\"\\n            );\\n            unchecked {\\n                _approve(owner, spender, currentAllowance - amount);\\n            }\\n        }\\n    }\\n}\"\r\n    }\r\n  },\r\n  \"settings\": {\r\n    \"optimizer\": {\r\n      \"enabled\": false,\r\n      \"runs\": 200\r\n    },\r\n    \"outputSelection\": {\r\n      \"*\": {\r\n        \"*\": [\r\n          \"evm.bytecode\",\r\n          \"evm.deployedBytecode\",\r\n          \"devdoc\",\r\n          \"userdoc\",\r\n          \"metadata\",\r\n          \"abi\"\r\n        ]\r\n      }\r\n    }\r\n  }\r\n}}", "ABI": "[{\"inputs\":[],\"stateMutability\":\"nonpayable\",\"type\":\"constructor\"},{\"anonymous\":false,\"inputs\":[{\"indexed\":true,\"internalType\":\"address\",\"name\":\"owner\",\"type\":\"address\"},{\"indexed\":true,\"internalType\":\"address\",\"name\":\"spender\",\"type\":\"address\"},{\"indexed\":false,\"internalType\":\"uint256\",\"name\":\"value\",\"type\":\"uint256\"}],\"name\":\"Approval\",\"type\":\"event\"},{\"anonymous\":false,\"inputs\":[{\"indexed\":true,\"internalType\":\"address\",\"name\":\"from\",\"type\":\"address\"},{\"indexed\":true,\"internalType\":\"address\",\"name\":\"to\",\"type\":\"address\"},{\"indexed\":false,\"internalType\":\"uint256\",\"name\":\"value\",\"type\":\"uint256\"}],\"name\":\"Transfer\",\"type\":\"event\"},{\"inputs\":[{\"internalType\":\"address\",\"name\":\"owner\",\"type\":\"address\"},{\"internalType\":\"address\",\"name\":\"spender\",\"type\":\"address\"}],\"name\":\"allowance\",\"outputs\":[{\"internalType\":\"uint256\",\"name\":\"\",\"type\":\"uint256\"}],\"stateMutability\":\"view\",\"type\":\"function\"},{\"inputs\":[{\"internalType\":\"address\",\"name\":\"spender\",\"type\":\"address\"},{\"internalType\":\"uint256\",\"name\":\"amount\",\"type\":\"uint256\"}],\"name\":\"approve\",\"outputs\":[{\"internalType\":\"bool\",\"name\":\"\",\"type\":\"bool\"}],\"stateMutability\":\"nonpayable\",\"type\":\"function\"},{\"inputs\":[{\"internalType\":\"address\",\"name\":\"account\",\"type\":\"address\"}],\"name\":\"balanceOf\",\"outputs\":[{\"internalType\":\"uint256\",\"name\":\"\",\"type\":\"uint256\"}],\"stateMutability\":\"view\",\"type\":\"function\"},{\"inputs\":[],\"name\":\"decimals\",\"outputs\":[{\"internalType\":\"uint8\",\"name\":\"\",\"type\":\"uint8\"}],\"stateMutability\":\"view\",\"type\":\"function\"},{\"inputs\":[],\"name\":\"name\",\"outputs\":[{\"internalType\":\"string\",\"name\":\"\",\"type\":\"string\"}],\"stateMutability\":\"view\",\"type\":\"function\"},{\"inputs\":[],\"name\":\"symbol\",\"outputs\":[{\"internalType\":\"string\",\"name\":\"\",\"type\":\"string\"}],\"stateMutability\":\"view\",\"type\":\"function\"},{\"inputs\":[],\"name\":\"totalSupply\",\"outputs\":[{\"internalType\":\"uint256\",\"name\":\"\",\"type\":\"uint256\"}],\"stateMutability\":\"view\",\"type\":\"function\"},{\"inputs\":[{\"internalType\":\"address\",\"name\":\"to\",\"type\":\"address\"},{\"internalType\":\"uint256\",\"name\":\"amount\",\"type\":\"uint256\"}],\"name\":\"transfer\",\"outputs\":[{\"internalType\":\"bool\",\"name\":\"\",\"type\":\"bool\"}],\"stateMutability\":\"nonpayable\",\"type\":\"function\"},{\"inputs\":[{\"internalType\":\"address\",\"name\":\"from\",\"type\":\"address\"},{\"internalType\":\"address\",\"name\":\"to\",\"type\":\"address\"},{\"internalType\":\"uint256\",\"name\":\"amount\",\"type\":\"uint256\"}],\"name\":\"transferFrom\",\"outputs\":[{\"internalType\":\"bool\",\"name\":\"\",\"type\":\"bool\"}],\"stateMutability\":\"nonpayable\",\"type\":\"function\"}]", "ContractName": "ERC20", "CompilerVersion": "v0.8.7+commit.e28d00a7", "OptimizationUsed": "0", "Runs": "200", "ConstructorArguments": "", "EVMVersion": "Default", "Library": "", "LicenseType": "", "Proxy": "0", "Implementation": "", "SwarmSource": ""}