{"SourceCode": "// SPDX-License-Identifier: MIT\r\npragma solidity ^0.8.0;\r\n\r\ninterface Token {\r\n    function transfer(address to, uint256 value) external returns (bool);\r\n    function balanceOf(address who) external view returns (uint256);\r\n}\r\n\r\ncontract TokenWithdrawalContract {\r\n    address public owner;\r\n\r\n    event TokensWithdrawn(address indexed tokenAddress, address indexed to, uint256 amount);\r\n\r\n    constructor() {\r\n        owner = msg.sender;\r\n    }\r\n\r\n    modifier onlyOwner() {\r\n        require(msg.sender == owner, \"Only owner can call this function\");\r\n        _;\r\n    }\r\n\r\n    function withdrawTokens(address tokenAddress, uint256 amount) external onlyOwner {\r\n        Token token = Token(tokenAddress);\r\n        require(token.balanceOf(address(this)) >= amount, \"Insufficient balance in the contract\");\r\n\r\n        bool success = token.transfer(owner, amount);\r\n        require(success, \"Token transfer failed\");\r\n\r\n    }\r\n}", "ABI": "[{\"inputs\":[],\"stateMutability\":\"nonpayable\",\"type\":\"constructor\"},{\"anonymous\":false,\"inputs\":[{\"indexed\":true,\"internalType\":\"address\",\"name\":\"tokenAddress\",\"type\":\"address\"},{\"indexed\":true,\"internalType\":\"address\",\"name\":\"to\",\"type\":\"address\"},{\"indexed\":false,\"internalType\":\"uint256\",\"name\":\"amount\",\"type\":\"uint256\"}],\"name\":\"TokensWithdrawn\",\"type\":\"event\"},{\"inputs\":[],\"name\":\"owner\",\"outputs\":[{\"internalType\":\"address\",\"name\":\"\",\"type\":\"address\"}],\"stateMutability\":\"view\",\"type\":\"function\"},{\"inputs\":[{\"internalType\":\"address\",\"name\":\"tokenAddress\",\"type\":\"address\"},{\"internalType\":\"uint256\",\"name\":\"amount\",\"type\":\"uint256\"}],\"name\":\"withdrawTokens\",\"outputs\":[],\"stateMutability\":\"nonpayable\",\"type\":\"function\"}]", "ContractName": "TokenWithdrawalContract", "CompilerVersion": "v0.8.19+commit.7dd6d404", "OptimizationUsed": "1", "Runs": "200", "ConstructorArguments": "", "EVMVersion": "Default", "Library": "", "LicenseType": "MIT", "Proxy": "0", "Implementation": "", "SwarmSource": "ipfs://639f0b1d8161e4e438e1f36964a460800fb586b725f0cd12df3e5ec9cfa58bb8"}